chrono_features/__init__.py
chrono_features/transformation_pipeline.py
chrono_features/ts_dataset.py
chrono_features/window_type.py
chrono_features/features/__init__.py
chrono_features/features/_base.py
chrono_features/features/absolute_energy.py
chrono_features/features/absolute_sum_of_changes.py
chrono_features/features/autocorrelation.py
chrono_features/features/linear_regression.py
chrono_features/features/max.py
chrono_features/features/mean.py
chrono_features/features/median.py
chrono_features/features/min.py
chrono_features/features/simple_moving_average.py
chrono_features/features/std.py
chrono_features/features/sum.py
chrono_features/features/weighted_mean.py
chrono_features/features/weighted_moving_average.py
chrono_features-0.0.15.dist-info/licenses/LICENSE
chrono_features-0.0.15.dist-info/METADATA
chrono_features-0.0.15.dist-info/WHEEL
chrono_features-0.0.15.dist-info/top_level.txt
chrono_features-0.0.15.dist-info/RECORD
