Metadata-Version: 2.4
Name: chrono_features
Version: 0.0.15
Summary: Generate features for TimeSeries
Author-email: Pritchin Ivan <ispritchin@gmail.com>
License: MIT License
Project-URL: Homepage, https://github.com/ISPritchin/chrono_features
Keywords: timeseries,features
Requires-Python: >=3.9
License-File: LICENSE
Requires-Dist: numpy>=1.20.0
Requires-Dist: polars>=0.15.0
Requires-Dist: numba>=0.55.0
Provides-Extra: dev
Requires-Dist: pytest>=7.0.0; extra == "dev"
Requires-Dist: rich>=13.0.0; extra == "dev"
Requires-Dist: ruff>=0.0.270; extra == "dev"
Requires-Dist: black>=23.0.0; extra == "dev"
Dynamic: license-file
